datocms/__init__.py
datocms/errors.py
datocms/node.py
datocms/utils.py
datocms/client/__init__.py
datocms/client/_async.py
datocms/client/_sync.py
datocms/client/auth.py
datocms/client/base.py
datocms/types/__init__.py
datocms/types/api.py
datocms/types/dast.py
datocms/types/errors.py
datocms/types/field.py
datocms/types/job.py
datocms/types/locale.py
datocms/types/model.py
datocms/types/record.py
datocms/types/relationships.py
datocms/types/upload.py
datocms-0.12.0.dist-info/METADATA
datocms-0.12.0.dist-info/WHEEL
datocms-0.12.0.dist-info/licenses/LICENSE
datocms-0.12.0.dist-info/RECORD
