Metadata-Version: 2.4
Name: datocms
Version: 0.12.0
Summary: Python libary for DatoCMS
Project-URL: Repository, https://github.com/rostyq/python-datocms
Author-email: Rostyslav Bohomaz <rostyslav.db@gmail.com>
License: MIT License
License-File: LICENSE
Keywords: datocms
Classifier: Programming Language :: Python :: 3
Requires-Python: >=3.11
Requires-Dist: httpx>=0.28.0
